vizarray/__init__.py
vizarray-0.1.0.dist-info/DESCRIPTION.rst
vizarray-0.1.0.dist-info/METADATA
vizarray-0.1.0.dist-info/RECORD
vizarray-0.1.0.dist-info/WHEEL
vizarray-0.1.0.dist-info/metadata.json
vizarray-0.1.0.dist-info/top_level.txt
