Metadata-Version: 2.0
Name: vizarray
Version: 0.1.0
Summary: Vizualize 1d and 2d NuymPy arrays
Home-page: https://github.com/ellisonbg/vizarray
Author: Brian E. Granger
Author-email: ellisonbg@gmail.com
License: Revised BSD
Platform: UNKNOWN
